omnivault/__init__.py
omnivault/py.typed
omnivault/_types/__init__.py
omnivault/_types/_alias.py
omnivault/_types/_generic.py
omnivault/_types/_newtype.py
omnivault/_types/_sentinel.py
omnivault/_types/sentinel.py
omnivault/benchmark/__init__.py
omnivault/benchmark/create_tensor_of_size.py
omnivault/benchmark/statistics.py
omnivault/constants/__init__.py
omnivault/constants/dtype.py
omnivault/constants/memory.py
omnivault/core/__init__.py
omnivault/core/logger.py
omnivault/distributed/__init__.py
omnivault/distributed/core.py
omnivault/distributed/dist_info.py
omnivault/distributed/logger.py
omnivault/dsa/__init__.py
omnivault/dsa/heap/priority_queue.py
omnivault/dsa/queue/deque.py
omnivault/dsa/searching_algorithms/__init__.py
omnivault/dsa/searching_algorithms/base.py
omnivault/dsa/searching_algorithms/context.py
omnivault/dsa/searching_algorithms/strategies.py
omnivault/dsa/stack/__init__.py
omnivault/dsa/stack/base.py
omnivault/dsa/stack/concrete.py
omnivault/linear_algebra/__init__.py
omnivault/linear_algebra/base.py
omnivault/linear_algebra/plotter.py
omnivault/linear_algebra/vector.py
omnivault/machine_learning/__init__.py
omnivault/machine_learning/estimator.py
omnivault/machine_learning/clustering/__init__.py
omnivault/machine_learning/clustering/kmeans.py
omnivault/machine_learning/metrics/__init__.py
omnivault/machine_learning/metrics/clustering/__init__.py
omnivault/machine_learning/metrics/clustering/supervised.py
omnivault/machine_learning/metrics/pairwise/__init__.py
omnivault/machine_learning/metrics/pairwise/distance.py
omnivault/modules/__init__.py
omnivault/modules/activation.py
omnivault/modules/lora.py
omnivault/modules/loss.py
omnivault/modules/module.py
omnivault/modules/nn_utils.py
omnivault/modules/pooling.py
omnivault/optimizers/__init__.py
omnivault/optimizers/adamw.py
omnivault/schedulers/__init__.py
omnivault/schedulers/cosine_annealing_warmup.py
omnivault/schedulers/utils.py
omnivault/transformer/__init__.py
omniverse-0.0.63.dist-info/LICENSE
omniverse-0.0.63.dist-info/METADATA
omniverse-0.0.63.dist-info/WHEEL
omniverse-0.0.63.dist-info/top_level.txt
omniverse-0.0.63.dist-info/RECORD
