Metadata-Version: 2.1
Name: omniverse
Version: 0.0.63
Summary: A collection of code for Omniverse.
Author-email: GAO Hongnan <hongnangao@gmail.com>
Project-URL: Homepage, https://github.com/gao-hongnan/omniverse
Project-URL: Issues, https://github.com/gao-hongnan/omniverse/issues
Classifier: Programming Language :: Python :: 3
Classifier: License :: OSI Approved :: Apache Software License
Classifier: Operating System :: OS Independent
Requires-Python: >=3.9
License-File: LICENSE
Requires-Dist: hydra-core==1.3.2
Requires-Dist: matplotlib<3.9.1,>=3.8.0
Requires-Dist: numpy<2.0.0,>=1.26.0
Requires-Dist: openai>=1.1.1
Requires-Dist: pandas>=2.1.1
Requires-Dist: portalocker>=2.8.2
Requires-Dist: pydantic==2.5.2
Requires-Dist: rich>=13.6.0
Requires-Dist: scikit-learn==1.5.0
Requires-Dist: seaborn>=0.13.0
Requires-Dist: tiktoken>=0.5.2
Requires-Dist: torch>=2.1.0
Requires-Dist: torchinfo>=1.8.0
Requires-Dist: torchtext
Requires-Dist: torchvision>=0.16.0
Provides-Extra: dev
Requires-Dist: bandit==1.7.5; extra == "dev"
Requires-Dist: black==23.10.1; extra == "dev"
Requires-Dist: colorama==0.4.6; extra == "dev"
Requires-Dist: cookiecutter==2.4.0; extra == "dev"
Requires-Dist: coverage==7.3.2; extra == "dev"
Requires-Dist: ghp-import==2.1.0; extra == "dev"
Requires-Dist: ipywidgets==7.7.2; extra == "dev"
Requires-Dist: isort==5.12.0; extra == "dev"
Requires-Dist: jupytext==1.15.2; extra == "dev"
Requires-Dist: jupyter-book==0.15.1; extra == "dev"
Requires-Dist: mypy==1.7.1; extra == "dev"
Requires-Dist: pandas-stubs==2.1.4.231227; extra == "dev"
Requires-Dist: pre-commit==3.6.0; extra == "dev"
Requires-Dist: pytest==7.4.3; extra == "dev"
Requires-Dist: pytest-mock==3.12.0; extra == "dev"
Requires-Dist: ruff==0.1.7; extra == "dev"
Requires-Dist: sphinx-proof==0.1.3; extra == "dev"
Requires-Dist: sphinx-sitemap==2.5.1; extra == "dev"
Requires-Dist: types-requests==2.31.0.10; extra == "dev"
Requires-Dist: types-tqdm==4.66.0.5; extra == "dev"
Requires-Dist: typeguard==4.1.5; extra == "dev"
Provides-Extra: serving
Requires-Dist: fastapi==0.109.2; extra == "serving"
Requires-Dist: uvicorn==0.27.1; extra == "serving"
Requires-Dist: gunicorn==21.2.0; extra == "serving"
Requires-Dist: Faker==23.2.0; extra == "serving"
Requires-Dist: sqlmodel==0.0.14; extra == "serving"
Requires-Dist: SQLAlchemy==2.0.22; extra == "serving"
Requires-Dist: pydantic==2.5.2; extra == "serving"
